setup.py
karura/__init__.py
karura/database_api.py
karura/default_config.py
karura/env.py
karura/run_server.py
karura.egg-info/PKG-INFO
karura.egg-info/SOURCES.txt
karura.egg-info/dependency_links.txt
karura.egg-info/requires.txt
karura.egg-info/top_level.txt
karura/bot/__init__.py
karura/bot/run.py
karura/bot/slackbot_settings.py
karura/bot/plugins/__init__.py
karura/bot/plugins/karura_bot.py
karura/core/__init__.py
karura/core/analysis_stop_exception.py
karura/core/analyst.py
karura/core/auto_run.py
karura/core/dataframe_extension.py
karura/core/description.py
karura/core/insight.py
karura/core/predictor.py
karura/core/insights/__init__.py
karura/core/insights/categorical_item_insight.py
karura/core/insights/categorical_to_dummy_insight.py
karura/core/insights/category_reduction_insight.py
karura/core/insights/column_ignorance_insight.py
karura/core/insights/datetime_to_categorical_insight.py
karura/core/insights/feature_selection_insight.py
karura/core/insights/label_format_insight.py
karura/core/insights/model_selection_insight.py
karura/core/insights/na_frequency_insight.py
karura/core/insights/numerical_scaling_insight.py
karura/core/insights/row_count_insight.py
karura/core/insights/target_confirmation_insight.py
karura/core/kintone/__init__.py
karura/core/kintone/application.py
karura/core/kintone/kintone_exception.py
karura/core/kintone/kintone_request.py
karura/server/__init__.py
karura/server/api.py
karura/server/message.py
karura/server/server.py
karura/server/site.py